smbus2/__init__.py
smbus2/py.typed
smbus2/smbus2.py
smbus2/smbus2.pyi
smbus2-0.4.3.dist-info/LICENSE
smbus2-0.4.3.dist-info/METADATA
smbus2-0.4.3.dist-info/WHEEL
smbus2-0.4.3.dist-info/top_level.txt
smbus2-0.4.3.dist-info/RECORD
