Metadata-Version: 2.1
Name: smbus2
Version: 0.4.3
Summary: smbus2 is a drop-in replacement for smbus-cffi/smbus-python in pure Python
Home-page: https://github.com/kplindegaard/smbus2
Author: Karl-Petter Lindegaard
Author-email: kp.lindegaard@gmail.com
License: MIT
Keywords: smbus,smbus2,python,i2c,raspberrypi,linux
Classifier: Development Status :: 4 - Beta
Classifier: Topic :: Utilities
Classifier: License :: OSI Approved :: MIT License
Classifier: Programming Language :: Python :: 2
Classifier: Programming Language :: Python :: 2.7
Classifier: Programming Language :: Python :: 3
Classifier: Programming Language :: Python :: 3.4
Classifier: Programming Language :: Python :: 3.5
Classifier: Programming Language :: Python :: 3.6
Classifier: Programming Language :: Python :: 3.7
Classifier: Programming Language :: Python :: 3.8
Classifier: Programming Language :: Python :: 3.9
Classifier: Programming Language :: Python :: 3.10
Classifier: Programming Language :: Python :: 3.11
Provides-Extra: docs
Provides-Extra: qa
Provides-Extra: test
License-File: LICENSE
